Workbook

Sheet 说明与假设
A1: 康方生物 (9926.HK) — AK112 + AK104 中国销售预测模型
A2: Base case｜单位:人民币亿元(除特别注明)｜模型为情景分析框架,蓝色单元格为可调输入｜编制日期 2026-06
A4: 一、模型范围与方法
A5: • | B5: 范围:仅测算 AK112(依沃西单抗)与 AK104(卡度尼利单抗)在中国大陆的处方药销售收入;不含海外(Summit/合作方分成)与其他管线产品。
A6: • | B6: 方法:自下而上「可治疗患者 × 渗透率 × 人均年实现净收入」分适应症测算;2024-2025 校准至公司已披露口径,2026-2030 为预测。
A7: • | B7: 口径:人均年实现净收入=已计入医保后单价、按真实治疗时长/早停折算后的『每位当年治疗患者实际确认收入』,故低于满疗程标价。
A8: • | B8: 渗透率定义:当年接受该药治疗的患者占该『适应症/用法』年可治疗患者的比例(含新发+维持)。
A9: • | B9: 重要提示:除公司已公布的合并口径外,分产品/分适应症拆分均为分析师估算,仅供框架推演,不构成投资建议。
A11: 二、关键锚点数据 (公司披露 / 公开来源)
A12: 指标 | B12: 数值 | C12: 口径 / 来源
A13: 2024 商业销售收入 | B13: 20.44 亿元 | C13: 公司年报,同比+25.34%(全部商业化产品合计)
A14: 2025 商业销售收入 | B14: 30.33 亿元 | C14: 公司2025年报(2026-03-26),RMB3,033.1mn,同比+51.48%
A15: 2025H1 商业销售收入 | B15: 14.02 亿元 | C15: 中期业绩,同比+49.2%
A16: 2025H1 卡度尼利收入 | B16: ≈7.06 亿元 | C16: 媒体/中报,较2024H1(6.06亿)+16.5%
A17: 依沃西医保单价 | B17: 736 元/瓶 | C17: 2025版医保;约15.9万元/年(满疗程标价)
A18: 依沃西累计治疗患者 | B18: ≈70,000 人 | C18: 公司2025年报(累计,截至2025末)
A19: 卡度尼利累计治疗患者 | B19: ≈120,000 人 | C19: 公司2025年报(累计)
A21: 三、颜色图例
A22: 蓝色 | B22: 硬编码输入 / 情景可调参数
A23: 黑色 | B23: 公式 / 计算结果
A24: 绿色 | B24: 跨表引用(链接其他工作表)
A26: 数据截至 2026-06；本模型不构成任何投资建议。

Sheet 依沃西AK112
A1: AK112 依沃西单抗 (PD-1/VEGF) — 中国销售预测
A2: 蓝色=可调输入；渗透率=当年接受治疗患者/该用法年可治疗患者；收入(亿元)=可治疗患者×(1+增速)^t×渗透率×人均年净收入(万元)/10000
A4: 一、关键假设
A5: 适应症 / 用法 | B5: 中国年可治疗 患者(2024,人) | C5: 市场 年增速 | D5: 人均年净 收入(万元) | E5: 渗透率 2024E | F5: 渗透率 2025E | G5: 渗透率 2026E | H5: 渗透率 2027E | I5: 渗透率 2028E | J5: 渗透率 2029E | K5: 渗透率 2030E
A6: 2L+ EGFRm NSCLC (HARMONi-A,+化疗) | B6: 60000 | C6: 0.03 | D6: 8 | E6: 0.07 | F6: 0.12 | G6: 0.16 | H6: 0.2 | I6: 0.23 | J6: 0.25 | K6: 0.27
A7: 1L PD-L1+ NSCLC 单药 (HARMONi-2) | B7: 150000 | C7: 0.03 | D7: 9 | E7: 0 | F7: 0.045 | G7: 0.09 | H7: 0.14 | I7: 0.18 | J7: 0.21 | K7: 0.24
A8: 1L 鳞状 NSCLC (+化疗, HARMONi-6) | B8: 90000 | C8: 0.03 | D8: 9.5 | E8: 0 | F8: 0 | G8: 0.08 | H8: 0.16 | I8: 0.22 | J8: 0.26 | K8: 0.29
A9: 1L 非鳞 NSCLC (+化疗, HARMONi-3/5) | B9: 120000 | C9: 0.03 | D9: 9.5 | E9: 0 | F9: 0 | G9: 0.04 | H9: 0.11 | I9: 0.17 | J9: 0.21 | K9: 0.24
A10: 其他实体瘤 (CRC/BTC/HCC 等, 期权) | B10: 200000 | C10: 0.04 | D10: 9 | E10: 0 | F10: 0 | G10: 0 | H10: 0.01 | I10: 0.03 | J10: 0.05 | K10: 0.08
A13: 二、收入预测
A14: 适应症 / 用法 (收入, 亿元) | E14: 2024E | F14: 2025E | G14: 2026E | H14: 2027E | I14: 2028E | J14: 2029E | K14: 2030E
A15: 2L+ EGFRm NSCLC (HARMONi-A,+化疗) | E15: =$B6*(1+$C6)^0*E6*$D6/10000 -> 3.36 | F15: =$B6*(1+$C6)^1*F6*$D6/10000 -> 5.9328 | G15: =$B6*(1+$C6)^2*G6*$D6/10000 -> 8.147712 | H15: =$B6*(1+$C6)^3*H6*$D6/10000 -> 10.490179 | I15: =$B6*(1+$C6)^4*I6*$D6/10000 -> 12.425617 | J15: =$B6*(1+$C6)^5*J6*$D6/10000 -> 13.911289 | K15: =$B6*(1+$C6)^6*K6*$D6/10000 -> 15.474918
A16: 1L PD-L1+ NSCLC 单药 (HARMONi-2) | E16: =$B7*(1+$C7)^0*E7*$D7/10000 -> 0 | F16: =$B7*(1+$C7)^1*F7*$D7/10000 -> 6.25725 | G16: =$B7*(1+$C7)^2*G7*$D7/10000 -> 12.889935 | H16: =$B7*(1+$C7)^3*H7*$D7/10000 -> 20.65254 | I16: =$B7*(1+$C7)^4*I7*$D7/10000 -> 27.349864 | J16: =$B7*(1+$C7)^5*J7*$D7/10000 -> 32.86542 | K16: =$B7*(1+$C7)^6*K7*$D7/10000 -> 38.687294
A17: 1L 鳞状 NSCLC (+化疗, HARMONi-6) | E17: =$B8*(1+$C8)^0*E8*$D8/10000 -> 0 | F17: =$B8*(1+$C8)^1*F8*$D8/10000 -> 0 | G17: =$B8*(1+$C8)^2*G8*$D8/10000 -> 7.256556 | H17: =$B8*(1+$C8)^3*H8*$D8/10000 -> 14.948505 | I17: =$B8*(1+$C8)^4*I8*$D8/10000 -> 21.170821 | J17: =$B8*(1+$C8)^5*J8*$D8/10000 -> 25.770663 | K17: =$B8*(1+$C8)^6*K8*$D8/10000 -> 29.606527
A18: 1L 非鳞 NSCLC (+化疗, HARMONi-3/5) | E18: =$B9*(1+$C9)^0*E9*$D9/10000 -> 0 | F18: =$B9*(1+$C9)^1*F9*$D9/10000 -> 0 | G18: =$B9*(1+$C9)^2*G9*$D9/10000 -> 4.837704 | H18: =$B9*(1+$C9)^3*H9*$D9/10000 -> 13.702797 | I18: =$B9*(1+$C9)^4*I9*$D9/10000 -> 21.812361 | J18: =$B9*(1+$C9)^5*J9*$D9/10000 -> 27.753021 | K18: =$B9*(1+$C9)^6*K9*$D9/10000 -> 32.669271
A19: 其他实体瘤 (CRC/BTC/HCC 等, 期权) | E19: =$B10*(1+$C10)^0*E10*$D10/10000 -> 0 | F19: =$B10*(1+$C10)^1*F10*$D10/10000 -> 0 | G19: =$B10*(1+$C10)^2*G10*$D10/10000 -> 0 | H19: =$B10*(1+$C10)^3*H10*$D10/10000 -> 2.0247552 | I19: =$B10*(1+$C10)^4*I10*$D10/10000 -> 6.3172362 | J19: =$B10*(1+$C10)^5*J10*$D10/10000 -> 10.949876 | K19: =$B10*(1+$C10)^6*K10*$D10/10000 -> 18.220594
A20: 合计 (亿元) | E20: =SUM(E15:E19) -> 3.36 | F20: =SUM(F15:F19) -> 12.19005 | G20: =SUM(G15:G19) -> 33.131907 | H20: =SUM(H15:H19) -> 61.818777 | I20: =SUM(I15:I19) -> 89.075899 | J20: =SUM(J15:J19) -> 111.25027 | K20: =SUM(K15:K19) -> 134.6586
A21: 估算当年治疗患者数 (人) | E21: =$B6*(1+$C6)^0*E6+$B7*(1+$C7)^0*E7+$B8*(1+$C8)^0*E8+$B9*(1+$C9)^0*E9+$B10*(1+$C10)^0*E10 -> 4200 | F21: =$B6*(1+$C6)^1*F6+$B7*(1+$C7)^1*F7+$B8*(1+$C8)^1*F8+$B9*(1+$C9)^1*F9+$B10*(1+$C10)^1*F10 -> 14368.5 | G21: =$B6*(1+$C6)^2*G6+$B7*(1+$C7)^2*G7+$B8*(1+$C8)^2*G8+$B9*(1+$C9)^2*G9+$B10*(1+$C10)^2*G10 -> 37237.59 | H21: =$B6*(1+$C6)^3*H6+$B7*(1+$C7)^3*H7+$B8*(1+$C8)^3*H8+$B9*(1+$C9)^3*H9+$B10*(1+$C10)^3*H10 -> 68468.984 | I21: =$B6*(1+$C6)^4*I6+$B7*(1+$C7)^4*I7+$B8*(1+$C8)^4*I8+$B9*(1+$C9)^4*I9+$B10*(1+$C10)^4*I10 -> 98185.365 | J21: =$B6*(1+$C6)^5*J6+$B7*(1+$C7)^5*J7+$B8*(1+$C8)^5*J8+$B9*(1+$C9)^5*J9+$B10*(1+$C10)^5*J10 -> 122413.49 | K21: =$B6*(1+$C6)^6*K6+$B7*(1+$C7)^6*K7+$B8*(1+$C8)^6*K8+$B9*(1+$C9)^6*K9+$B10*(1+$C10)^6*K10 -> 148128.11
A22: 2025E→2030E 收入 CAGR | B22: =(K20/F20)^(1/5)-1 -> 0.61676063

Sheet 卡度尼利AK104
A1: AK104 卡度尼利单抗 (PD-1/CTLA-4) — 中国销售预测
A2: 蓝色=可调输入；渗透率=当年接受治疗患者/该用法年可治疗患者；收入(亿元)=可治疗患者×(1+增速)^t×渗透率×人均年净收入(万元)/10000
A4: 一、关键假设
A5: 适应症 / 用法 | B5: 中国年可治疗 患者(2024,人) | C5: 市场 年增速 | D5: 人均年净 收入(万元) | E5: 渗透率 2024E | F5: 渗透率 2025E | G5: 渗透率 2026E | H5: 渗透率 2027E | I5: 渗透率 2028E | J5: 渗透率 2029E | K5: 渗透率 2030E
A6: 1L 宫颈癌 (+化疗±贝伐, COMPASSION-16) | B6: 40000 | C6: 0.03 | D6: 10 | E6: 0.1 | F6: 0.18 | G6: 0.24 | H6: 0.28 | I6: 0.31 | J6: 0.33 | K6: 0.34
A7: 2L+ 宫颈癌 (单药, COMPASSION-03) | B7: 25000 | C7: 0.02 | D7: 9 | E7: 0.12 | F7: 0.15 | G7: 0.17 | H7: 0.18 | I7: 0.19 | J7: 0.2 | K7: 0.2
A8: 1L 胃/GEJ 腺癌 (+化疗, COMPASSION-15) | B8: 150000 | C8: 0.02 | D8: 10 | E8: 0.01 | F8: 0.03 | G8: 0.06 | H8: 0.09 | I8: 0.11 | J8: 0.12 | K8: 0.13
A9: 其他 (HCC/肺/肝胆等, 期权) | B9: 180000 | C9: 0.03 | D9: 9.5 | E9: 0 | F9: 0 | G9: 0.01 | H9: 0.03 | I9: 0.05 | J9: 0.07 | K9: 0.09
A12: 二、收入预测
A13: 适应症 / 用法 (收入, 亿元) | E13: 2024E | F13: 2025E | G13: 2026E | H13: 2027E | I13: 2028E | J13: 2029E | K13: 2030E
A14: 1L 宫颈癌 (+化疗±贝伐, COMPASSION-16) | E14: =$B6*(1+$C6)^0*E6*$D6/10000 -> 4 | F14: =$B6*(1+$C6)^1*F6*$D6/10000 -> 7.416 | G14: =$B6*(1+$C6)^2*G6*$D6/10000 -> 10.18464 | H14: =$B6*(1+$C6)^3*H6*$D6/10000 -> 12.238542 | I14: =$B6*(1+$C6)^4*I6*$D6/10000 -> 13.956309 | J14: =$B6*(1+$C6)^5*J6*$D6/10000 -> 15.302418 | K14: =$B6*(1+$C6)^6*K6*$D6/10000 -> 16.239111
A15: 2L+ 宫颈癌 (单药, COMPASSION-03) | E15: =$B7*(1+$C7)^0*E7*$D7/10000 -> 2.7 | F15: =$B7*(1+$C7)^1*F7*$D7/10000 -> 3.4425 | G15: =$B7*(1+$C7)^2*G7*$D7/10000 -> 3.97953 | H15: =$B7*(1+$C7)^3*H7*$D7/10000 -> 4.2978924 | I15: =$B7*(1+$C7)^4*I7*$D7/10000 -> 4.6273975 | J15: =$B7*(1+$C7)^5*J7*$D7/10000 -> 4.9683636 | K15: =$B7*(1+$C7)^6*K7*$D7/10000 -> 5.0677309
A16: 1L 胃/GEJ 腺癌 (+化疗, COMPASSION-15) | E16: =$B8*(1+$C8)^0*E8*$D8/10000 -> 1.5 | F16: =$B8*(1+$C8)^1*F8*$D8/10000 -> 4.59 | G16: =$B8*(1+$C8)^2*G8*$D8/10000 -> 9.3636 | H16: =$B8*(1+$C8)^3*H8*$D8/10000 -> 14.326308 | I16: =$B8*(1+$C8)^4*I8*$D8/10000 -> 17.860131 | J16: =$B8*(1+$C8)^5*J8*$D8/10000 -> 19.873454 | K16: =$B8*(1+$C8)^6*K8*$D8/10000 -> 21.960167
A17: 其他 (HCC/肺/肝胆等, 期权) | E17: =$B9*(1+$C9)^0*E9*$D9/10000 -> 0 | F17: =$B9*(1+$C9)^1*F9*$D9/10000 -> 0 | G17: =$B9*(1+$C9)^2*G9*$D9/10000 -> 1.814139 | H17: =$B9*(1+$C9)^3*H9*$D9/10000 -> 5.6056895 | I17: =$B9*(1+$C9)^4*I9*$D9/10000 -> 9.6231003 | J17: =$B9*(1+$C9)^5*J9*$D9/10000 -> 13.876511 | K17: =$B9*(1+$C9)^6*K9*$D9/10000 -> 18.376465
A18: 合计 (亿元) | E18: =SUM(E14:E17) -> 8.2 | F18: =SUM(F14:F17) -> 15.4485 | G18: =SUM(G14:G17) -> 25.341909 | H18: =SUM(H14:H17) -> 36.468432 | I18: =SUM(I14:I17) -> 46.066938 | J18: =SUM(J14:J17) -> 54.020747 | K18: =SUM(K14:K17) -> 61.643474
A19: 估算当年治疗患者数 (人) | E19: =$B6*(1+$C6)^0*E6+$B7*(1+$C7)^0*E7+$B8*(1+$C8)^0*E8+$B9*(1+$C9)^0*E9 -> 8500 | F19: =$B6*(1+$C6)^1*F6+$B7*(1+$C7)^1*F7+$B8*(1+$C8)^1*F8+$B9*(1+$C9)^1*F9 -> 15831 | G19: =$B6*(1+$C6)^2*G6+$B7*(1+$C7)^2*G7+$B8*(1+$C8)^2*G8+$B9*(1+$C9)^2*G9 -> 25879.56 | H19: =$B6*(1+$C6)^3*H6+$B7*(1+$C7)^3*H7+$B8*(1+$C8)^3*H8+$B9*(1+$C9)^3*H9 -> 37241.012 | I19: =$B6*(1+$C6)^4*I6+$B7*(1+$C7)^4*I7+$B8*(1+$C8)^4*I8+$B9*(1+$C9)^4*I9 -> 47087.572 | J19: =$B6*(1+$C6)^5*J6+$B7*(1+$C7)^5*J7+$B8*(1+$C8)^5*J8+$B9*(1+$C9)^5*J9 -> 55303.13 | K19: =$B6*(1+$C6)^6*K6+$B7*(1+$C7)^6*K7+$B8*(1+$C8)^6*K8+$B9*(1+$C9)^6*K9 -> 63173.738
A20: 2025E→2030E 收入 CAGR | B20: =(K18/F18)^(1/5)-1 -> 0.31886444

Sheet 汇总与敏感性
A1: 汇总：AK112 + AK104 中国销售预测 与 敏感性分析
A2: 单位：人民币亿元；绿色=跨表引用各产品合计
A4: 一、分产品收入预测 (亿元)
A5: 产品 | E5: 2024E | F5: 2025E | G5: 2026E | H5: 2027E | I5: 2028E | J5: 2029E | K5: 2030E
A6: AK112 依沃西单抗 | E6: =依沃西AK112!E20 -> 3.36 | F6: =依沃西AK112!F20 -> 12.19005 | G6: =依沃西AK112!G20 -> 33.131907 | H6: =依沃西AK112!H20 -> 61.818777 | I6: =依沃西AK112!I20 -> 89.075899 | J6: =依沃西AK112!J20 -> 111.25027 | K6: =依沃西AK112!K20 -> 134.6586
A7: AK104 卡度尼利单抗 | E7: =卡度尼利AK104!E18 -> 8.2 | F7: =卡度尼利AK104!F18 -> 15.4485 | G7: =卡度尼利AK104!G18 -> 25.341909 | H7: =卡度尼利AK104!H18 -> 36.468432 | I7: =卡度尼利AK104!I18 -> 46.066938 | J7: =卡度尼利AK104!J18 -> 54.020747 | K7: =卡度尼利AK104!K18 -> 61.643474
A8: 两大双抗合计 | E8: =SUM(E6:E7) -> 11.56 | F8: =SUM(F6:F7) -> 27.63855 | G8: =SUM(G6:G7) -> 58.473816 | H8: =SUM(H6:H7) -> 98.287209 | I8: =SUM(I6:I7) -> 135.14284 | J8: =SUM(J6:J7) -> 165.27102 | K8: =SUM(K6:K7) -> 196.30208
A9: 同比增速 | E9: n/a | F9: =F8/E8-1 -> 1.390878 | G9: =G8/F8-1 -> 1.1156615 | H9: =H8/G8-1 -> 0.68087557 | I9: =I8/H8-1 -> 0.37497888 | J9: =J8/I8-1 -> 0.22293582 | K9: =K8/J8-1 -> 0.18775865
A11: 备忘：公司合并商业销售收入(全部产品,公司披露)
A12: 2024A = 20.44 亿元(实际) | E12: ↑ 含其他5款商业化产品；本模型仅测算两大双抗
A13: 2025A = 30.33 亿元(实际)
A15: 二、敏感性分析 — 2030E 两大双抗合计收入 (亿元)
A16: 行=渗透率乘数；列=净价乘数(相对Base)。Base(乘数1.0)=K8。收入对两者均为线性。
B18: 净价乘数→ | C18: 0.85 | D18: 0.925 | E18: 1 | F18: 1.075 | G18: 1.15
A19: 渗透率乘数↓ | B19: 0.7 | C19: =$K$8*$B19*C$18 -> 116.79974 | D19: =$K$8*$B19*D$18 -> 127.1056 | E19: =$K$8*$B19*E$18 -> 137.41145 | F19: =$K$8*$B19*F$18 -> 147.71731 | G19: =$K$8*$B19*G$18 -> 158.02317
B20: 0.85 | C20: =$K$8*$B20*C$18 -> 141.82825 | D20: =$K$8*$B20*D$18 -> 154.34251 | E20: =$K$8*$B20*E$18 -> 166.85677 | F20: =$K$8*$B20*F$18 -> 179.37102 | G20: =$K$8*$B20*G$18 -> 191.88528
B21: 1 | C21: =$K$8*$B21*C$18 -> 166.85677 | D21: =$K$8*$B21*D$18 -> 181.57942 | E21: =$K$8*$B21*E$18 -> 196.30208 | F21: =$K$8*$B21*F$18 -> 211.02473 | G21: =$K$8*$B21*G$18 -> 225.74739
B22: 1.15 | C22: =$K$8*$B22*C$18 -> 191.88528 | D22: =$K$8*$B22*D$18 -> 208.81634 | E22: =$K$8*$B22*E$18 -> 225.74739 | F22: =$K$8*$B22*F$18 -> 242.67844 | G22: =$K$8*$B22*G$18 -> 259.6095
B23: 1.3 | C23: =$K$8*$B23*C$18 -> 216.9138 | D23: =$K$8*$B23*D$18 -> 236.05325 | E23: =$K$8*$B23*E$18 -> 255.1927 | F23: =$K$8*$B23*F$18 -> 274.33215 | G23: =$K$8*$B23*G$18 -> 293.47161
